vceffort/__init__.py
vceffort/extractors.py
vceffort/worklog.py
vceffort-0.3.5.dist-info/DESCRIPTION.rst
vceffort-0.3.5.dist-info/METADATA
vceffort-0.3.5.dist-info/RECORD
vceffort-0.3.5.dist-info/WHEEL
vceffort-0.3.5.dist-info/entry_points.txt
vceffort-0.3.5.dist-info/metadata.json
vceffort-0.3.5.dist-info/top_level.txt
