Metadata-Version: 2.0
Name: vceffort
Version: 0.3.5
Summary: A script to estimate development hours from version control system log(s)
Home-page: https://bitbucket.com/tim_littlefair/vceffort
Author: Tim Littlefair
Author-email: tim_littlefair@hotmail.com
License: MIT
Keywords: version control,metrics,example
Platform: UNKNOWN
Classifier: Development Status :: 3 - Alpha
Classifier: Intended Audience :: Developers
Classifier: Operating System :: OS Independent
Classifier: Programming Language :: Python :: 3
